{"Biruk Zewdu": {"phone": "0945367823", "email": "birukzewdu245@gmail.com", "last_contact": "2025-03-01", "category": "Friend", "interactions": ["2025-01-15", "2025-03-01"]}, "yilkal Kebede": {"phone": "0972123256", "email": "yheys345@gmail.com", "last_contact": "2025-05-10", "category": "Family", "interactions": ["2025-04-28", "2025-05-10"]}, "Endale Biru": {"phone": "0965743613", "email": "endalebiru03@gmail.com", "last_contact": "2025-05-25", "category": "Family", "interactions": ["2025-04-29", "2025-05-15", "2025-05-25"]}, "Meklit Kiros": {"phone": "0990345632", "email": "meklitkir76@gmail.com", "last_contact": "2024-12-10", "category": "Friend", "interactions": ["2024-09-10", "2024-12-10"]}, "Dawit Gebru": {"phone": "0923871536", "email": "daveg824@gmail.com", "last_contact": "2025-06-01", "category": "friend", "interactions": ["2025-06-01"]}}